setup.py
GauminWriter.egg-info/PKG-INFO
GauminWriter.egg-info/SOURCES.txt
GauminWriter.egg-info/dependency_links.txt
GauminWriter.egg-info/entry_points.txt
GauminWriter.egg-info/not-zip-safe
GauminWriter.egg-info/requires.txt
GauminWriter.egg-info/top_level.txt
gauminwriter/__init__.py
gauminwriter/__main__.py
gauminwriter/main.py
gauminwriter/writer.kv
gauminwriter/imgs/empty.png
gauminwriter/imgs/gaumin_logo.png