Metadata-Version: 1.0
Name: GauminWriter
Version: 0.1
Summary: Interactive book editor
Home-page: http://lagunak.gisa-elkartea.org/projects/gauminipuin/
Author: Ales Zabala Alava (Shagi)
Author-email: shagi@gisa-elkartea.org
License: GPLv3+
Platform: UNKNOWN
